postquick/__init__.py
postquick_py-1.0.8.dist-info/DESCRIPTION.rst
postquick_py-1.0.8.dist-info/METADATA
postquick_py-1.0.8.dist-info/RECORD
postquick_py-1.0.8.dist-info/WHEEL
postquick_py-1.0.8.dist-info/metadata.json
postquick_py-1.0.8.dist-info/top_level.txt
