Metadata-Version: 2.0
Name: postquick-py
Version: 1.0.8
Summary: PostQuick Python client
Home-page: UNKNOWN
Author: Startnet Co
Author-email: UNKNOWN
License: GNU General Public License v2 (GPLv2)
Keywords: websocket real-time pubsub
Platform: UNKNOWN
Classifier: Development Status :: 3 - Alpha
Classifier: Intended Audience :: Developers
Classifier: Topic :: Software Development :: Build Tools
Classifier: License :: OSI Approved :: GNU General Public License v2 (GPLv2)
Classifier: Programming Language :: Python :: 2
Classifier: Programming Language :: Python :: 2.7
Classifier: Programming Language :: Python :: 3
Classifier: Programming Language :: Python :: 3.3
Classifier: Programming Language :: Python :: 3.4
Classifier: Programming Language :: Python :: 3.5
Requires-Dist: socketIO-client-nexus
